{
  "project_info": {
    "project_number": "274334378155",
    "project_id": "cuidapet-11dc8",
    "storage_bucket": "cuidapet-11dc8.firebasestorage.app"
  },
  "client": [
    {
      "client_info": {
        "mobilesdk_app_id": "1:274334378155:android:9573314ac39d57ef27efee",
        "android_client_info": {
          "package_name": "dev.samu.cuidapet"
        }
      },
      "oauth_client": [],
      "api_key": [
        {
          "current_key": "AIzaSyAOUmTFnM9hA_1TJyPtDsZYGMJnRjFPjU0"
        }
      ],
      "services": {
        "appinvite_service": {
          "other_platform_oauth_client": []
        }
      }
    }
  ],
  "configuration_version": "1"
}